crudrouter/__init__.py
crudrouter/_base.py
crudrouter/_json_api.py
crudrouter/_tinydb_crud.py
crudrouter/tinydb.py
LICENSE.md
crudrouter-0.1.2.dist-info/LICENSE.md
crudrouter-0.1.2.dist-info/WHEEL
crudrouter-0.1.2.dist-info/METADATA
crudrouter-0.1.2.dist-info/RECORD
