Metadata-Version: 2.1
Name: crudrouter
Version: 0.1.2
Summary: 
Home-page: https://code.shipyard.blackpearl.us/bma/sscp/crudrouter
Author: Benjamin Harruff
Author-email: harruff.benjamin@solute.us
Requires-Python: >=3.8,<4.0
Classifier: Programming Language :: Python :: 3
Classifier: Programming Language :: Python :: 3.8
Requires-Dist: fastapi (>=0.62.0,<0.63.0)
Requires-Dist: loguru (>=0.5.3,<0.6.0)
Requires-Dist: pydantic (>=1.8.2,<2.0.0)
Requires-Dist: tinydb (>=4.5.1,<5.0.0)
Requires-Dist: uuid (>=1.30,<2.0)
Requires-Dist: uvicorn (>=0.11.8,<0.12.0)
Project-URL: Repository, https://code.shipyard.blackpearl.us/bma/sscp/crudrouter
